{
  "name": "@quojs/core",
  "entries": [
    {
      "version": "0.6.0",
      "tag": "@quojs/core_v0.6.0",
      "date": "Fri, 23 Jan 2026 21:05:12 GMT",
      "comments": {
        "minor": [
          {
            "comment": "feat(core): remove deprecated methods and typings, update docs and examples"
          }
        ]
      }
    },
    {
      "version": "0.5.0",
      "tag": "@quojs/core_v0.5.0",
      "date": "Thu, 08 Jan 2026 08:01:50 GMT",
      "comments": {
        "minor": [
          {
            "comment": "License change from Mozilla Public License 2.0 to MIT License"
          }
        ],
        "none": [
          {
            "comment": "Adopt event-bus terminology for v0.5.0"
          }
        ]
      }
    },
    {
      "version": "0.4.0",
      "tag": "@quojs/core_v0.4.0",
      "date": "Tue, 30 Dec 2025 06:20:03 GMT",
      "comments": {
        "minor": [
          {
            "comment": "Republish after npm unpublish (no code changes)."
          }
        ]
      }
    },
    {
      "version": "0.3.0",
      "tag": "@quojs/core_v0.3.0",
      "date": "Tue, 09 Dec 2025 02:16:26 GMT",
      "comments": {
        "none": [
          {
            "comment": "chore(core): devDeps – bump Vite for security"
          }
        ],
        "minor": [
          {
            "comment": "fix(core): [@quojs/core] - improve core build config"
          }
        ]
      }
    },
    {
      "version": "0.2.0",
      "tag": "@quojs/core_v0.2.0",
      "date": "Tue, 04 Nov 2025 06:18:56 GMT",
      "comments": {
        "minor": [
          {
            "comment": "initial public release"
          }
        ],
        "none": [
          {
            "comment": "docs(core,react): regenerate API docs using TypeDoc (no API changes)"
          }
        ],
        "patch": [
          {
            "comment": "docs(core): add multi-lang docs"
          }
        ]
      }
    }
  ]
}
